replyify/__init__.py
replyify/api.py
replyify/exceptions.py
replyify/http_client.py
replyify/resources.py
replyify/utils.py
replyify/version.py
replyify/data/cacert-2017-01-18.pem
replyify-0.1.0.dist-info/LICENSE
replyify-0.1.0.dist-info/METADATA
replyify-0.1.0.dist-info/WHEEL
replyify-0.1.0.dist-info/top_level.txt
replyify-0.1.0.dist-info/RECORD
