Metadata-Version: 2.1
Name: replyify
Version: 0.1.0
Summary: Replyify REST API Client
Home-page: http://github.com/replyify/replyify-python
Author: Replyify
Author-email: team@replyify.com
License: MIT
Keywords: replyify rest api client
Platform: UNKNOWN
Classifier: Development Status :: 3 - Alpha
Classifier: Intended Audience :: Developers
Classifier: License :: OSI Approved :: MIT License
Classifier: Operating System :: OS Independent
Classifier: Programming Language :: Python
Classifier: Programming Language :: Python :: 2
Classifier: Programming Language :: Python :: 2.6
Classifier: Programming Language :: Python :: 2.7
Classifier: Programming Language :: Python :: 3.6
Classifier: Topic :: Software Development :: Libraries :: Python Modules
Requires-Dist: requests (>=0.8.8)
